LICENSE
MANIFEST.in
README.md
README.rst
VERSION
requirements.txt
setup.py
setupmeta.py
dido/__init__.py
dido.egg-info/PKG-INFO
dido.egg-info/SOURCES.txt
dido.egg-info/dependency_links.txt
dido.egg-info/requires.txt
dido.egg-info/top_level.txt